pynndb2cli/__init__.py
pynndb2cli/__main__.py
pynndb2cli/commands.py
pynndb2cli/completers.py
pynndb2cli/parsers.py
pynndb2cli/prettyprint.py
pynndb2cli-2.0.5.data/data/Pipfile
pynndb2cli-2.0.5.data/data/requirements.txt
pynndb2cli-2.0.5.dist-info/LICENSE
pynndb2cli-2.0.5.dist-info/METADATA
pynndb2cli-2.0.5.dist-info/WHEEL
pynndb2cli-2.0.5.dist-info/entry_points.txt
pynndb2cli-2.0.5.dist-info/top_level.txt
pynndb2cli-2.0.5.dist-info/RECORD
