Metadata-Version: 2.1
Name: pynndb2cli
Version: 2.0.5
Summary: PyNNDB2 CLI
Home-page: https://gitlab.com/oddjobz/pynndb2-cli
Author: Gareth Bult
Author-email: gareth@bult.co.uk
License: MIT
Keywords: pynndb2,cli,shell,python,database
Platform: UNKNOWN
Classifier: Development Status :: 3 - Alpha
Classifier: Intended Audience :: Developers
Classifier: Topic :: Database :: Database Engines/Servers
Classifier: License :: OSI Approved :: MIT License
Classifier: Programming Language :: Python :: 3
Requires-Dist: ujson
Requires-Dist: cmd2
Requires-Dist: pynndb2
Requires-Dist: termcolor
Requires-Dist: ascii-graph
Requires-Dist: pygments
Requires-Dist: Pipfile
